mssql_crud_operations/__init__.py
tests/__init__.py
tests/test_mssql_crud_operations.py
mssql_crud_operations-0.1.dist-info/METADATA
mssql_crud_operations-0.1.dist-info/WHEEL
mssql_crud_operations-0.1.dist-info/top_level.txt
mssql_crud_operations-0.1.dist-info/RECORD
