Metadata-Version: 2.1
Name: mssql-crud-operations
Version: 0.1
Summary: UNKNOWN
Home-page: UNKNOWN
License: UNKNOWN
Platform: UNKNOWN
Requires-Dist: pyodbc
Requires-Dist: python-dotenv
